ebird/scrapers/__init__.py
ebird/scrapers/checklists.py
ebird/scrapers/recent.py
ebird_scrapers-0.2.2.dist-info/METADATA
ebird_scrapers-0.2.2.dist-info/WHEEL
ebird_scrapers-0.2.2.dist-info/top_level.txt
ebird_scrapers-0.2.2.dist-info/RECORD
